morris_lee_package/__init__.py
morris_lee_package/morris_coding.py
morris_learning-0.0.4.dist-info/LICENSE
morris_learning-0.0.4.dist-info/METADATA
morris_learning-0.0.4.dist-info/WHEEL
morris_learning-0.0.4.dist-info/top_level.txt
morris_learning-0.0.4.dist-info/RECORD
