Metadata-Version: 2.1
Name: morris-learning
Version: 0.0.4
Summary: A tool  to simply common data analysis
Home-page: https://github.com/k-w-lee/good-life
Author: Morris Lee
Author-email: info.leekahwin@gmail.com
Project-URL: Bug Tracker, https://github.com/k-w-lee/good-life/issues
Classifier: Programming Language :: Python :: 3
Classifier: License :: OSI Approved :: MIT License
Classifier: Operating System :: OS Independent
Requires-Python: >=3.6
License-File: LICENSE
